{
  "tipo": "Aff | sub",
  "cantiere": {
    "indirizzo": "stringa",
    "civico": "numero",
    "cap": "numero",
    "comune": "stringa",
    "responsabileLavori": "stringa",
    "imprese": "array di imprese"
  },
  "anagrafica": {
    "nome": "Luigi",
    "cognome": "Pierorazio",
    "dataNascita": "2022-11-01",
    "luogoNascita": "Palena",
    "codiceFiscale": "naonuahfuh",
    "impresa": "Pierorazio costruzione",
    "datoreLavoro": true
  },
  "macchine": "array di macchine",
  "maestranze": "array maestranze",
  "impreseSubappaltatrici": "array imprese",
  "documentiIdoneitaImpresa": [
    {
      "autodichiarazione": {
        "nome": "stringa",
        "presenza": true
      },
      "file": "tipo file (opzionale)"
    }
  ],
  "comunicazioni": "vedere xd",
}